examples/01-base.py
examples/02-progress.py
examples/03-revoke.py
examples/04-secure-revoke.py
examples/05-multiple.py
examples/06-chaining.py
examples/07-async-task.py
examples/08-pickle-serializer.py
examples/__init__.py
flowgrid/__init__.py
flowgrid/__main__.py
flowgrid/base.py
flowgrid/celery_app.py
flowgrid/cli.py
flowgrid/config.py
flowgrid/lazy_import.py
py_flowgrid-0.3.7.dist-info/LICENSE
py_flowgrid-0.3.7.dist-info/METADATA
py_flowgrid-0.3.7.dist-info/WHEEL
py_flowgrid-0.3.7.dist-info/entry_points.txt
py_flowgrid-0.3.7.dist-info/top_level.txt
py_flowgrid-0.3.7.dist-info/RECORD
