Metadata-Version: 2.1
Name: py-flowgrid
Version: 0.3.7
Summary: A simplified, powerful interface for distributed task management in Python, built on Celery.
Home-page: https://github.com/fernaper/flowgrid
Author: Fernando Pérez
Author-email: fernaperg@gmail.com
License: MIT
License-File: LICENSE
Requires-Dist: celery ==5.4.0
Requires-Dist: redis ==5.0.8
Requires-Dist: watchdog ==4.0.0
